[
  {
    "lines": [
      {
        "text": "DO AUTOR DE SAPIENS",
        "boundingPolygon": [
          {
            "x": 226,
            "y": 62
          },
          {
            "x": 817,
            "y": 63
          },
          {
            "x": 817,
            "y": 110
          },
          {
            "x": 226,
            "y": 110
          }
        ],
        "words": [
          {
            "text": "DO",
            "boundingPolygon": [
              {
                "x": 228,
                "y": 63
              },
              {
                "x": 293,
                "y": 63
              },
              {
                "x": 291,
                "y": 111
              },
              {
                "x": 226,
                "y": 110
              }
            ],
            "confidence": 0.999
          },
          {
            "text": "AUTOR",
            "boundingPolygon": [
              {
                "x": 325,
                "y": 63
              },
              {
                "x": 503,
                "y": 63
              },
              {
                "x": 502,
                "y": 111
              },
              {
                "x": 324,
                "y": 111
              }
            ],
            "confidence": 0.997
          },
          {
            "text": "DE",
            "boundingPolygon": [
              {
                "x": 526,
                "y": 63
              },
              {
                "x": 591,
                "y": 63
              },
              {
                "x": 590,
                "y": 111
              },
              {
                "x": 525,
                "y": 111
              }
            ],
            "confidence": 0.997
          },
          {
            "text": "SAPIENS",
            "boundingPolygon": [
              {
                "x": 614,
                "y": 63
              },
              {
                "x": 817,
                "y": 64
              },
              {
                "x": 816,
                "y": 111
              },
              {
                "x": 613,
                "y": 111
              }
            ],
            "confidence": 0.99
          }
        ]
      },
      {
        "text": "Yuval Noah Harari",
        "boundingPolygon": [
          {
            "x": 102,
            "y": 142
          },
          {
            "x": 940,
            "y": 143
          },
          {
            "x": 940,
            "y": 231
          },
          {
            "x": 102,
            "y": 230
          }
        ],
        "words": [
          {
            "text": "Yuval",
            "boundingPolygon": [
              {
                "x": 109,
                "y": 142
              },
              {
                "x": 350,
                "y": 143
              },
              {
                "x": 350,
                "y": 231
              },
              {
                "x": 109,
                "y": 231
              }
            ],
            "confidence": 0.995
          },
          {
            "text": "Noah",
            "boundingPolygon": [
              {
                "x": 367,
                "y": 143
              },
              {
                "x": 602,
                "y": 145
              },
              {
                "x": 602,
                "y": 230
              },
              {
                "x": 367,
                "y": 231
              }
            ],
            "confidence": 0.989
          },
          {
            "text": "Harari",
            "boundingPolygon": [
              {
                "x": 643,
                "y": 145
              },
              {
                "x": 941,
                "y": 148
              },
              {
                "x": 941,
                "y": 230
              },
              {
                "x": 643,
                "y": 230
              }
            ],
            "confidence": 0.988
          }
        ]
      },
      {
        "text": "HOMO",
        "boundingPolygon": [
          {
            "x": 187,
            "y": 908
          },
          {
            "x": 853,
            "y": 908
          },
          {
            "x": 853,
            "y": 1064
          },
          {
            "x": 187,
            "y": 1065
          }
        ],
        "words": [
          {
            "text": "HOMO",
            "boundingPolygon": [
              {
                "x": 191,
                "y": 909
              },
              {
                "x": 777,
                "y": 913
              },
              {
                "x": 776,
                "y": 1064
              },
              {
                "x": 187,
                "y": 1066
              }
            ],
            "confidence": 0.993
          }
        ]
      },
      {
        "text": "DEUS",
        "boundingPolygon": [
          {
            "x": 191,
            "y": 1082
          },
          {
            "x": 849,
            "y": 1086
          },
          {
            "x": 848,
            "y": 1262
          },
          {
            "x": 191,
            "y": 1259
          }
        ],
        "words": [
          {
            "text": "DEUS",
            "boundingPolygon": [
              {
                "x": 191,
                "y": 1083
              },
              {
                "x": 817,
                "y": 1087
              },
              {
                "x": 817,
                "y": 1262
              },
              {
                "x": 191,
                "y": 1261
              }
            ],
            "confidence": 0.992
          }
        ]
      },
      {
        "text": "Uma breve hist처ria do amanh찾",
        "boundingPolygon": [
          {
            "x": 196,
            "y": 1278
          },
          {
            "x": 849,
            "y": 1278
          },
          {
            "x": 849,
            "y": 1324
          },
          {
            "x": 196,
            "y": 1324
          }
        ],
        "words": [
          {
            "text": "Uma",
            "boundingPolygon": [
              {
                "x": 196,
                "y": 1280
              },
              {
                "x": 299,
                "y": 1280
              },
              {
                "x": 299,
                "y": 1324
              },
              {
                "x": 196,
                "y": 1324
              }
            ],
            "confidence": 0.999
          },
          {
            "text": "breve",
            "boundingPolygon": [
              {
                "x": 311,
                "y": 1280
              },
              {
                "x": 429,
                "y": 1280
              },
              {
                "x": 428,
                "y": 1324
              },
              {
                "x": 311,
                "y": 1324
              }
            ],
            "confidence": 0.998
          },
          {
            "text": "hist처ria",
            "boundingPolygon": [
              {
                "x": 438,
                "y": 1280
              },
              {
                "x": 603,
                "y": 1279
              },
              {
                "x": 602,
                "y": 1325
              },
              {
                "x": 438,
                "y": 1324
              }
            ],
            "confidence": 0.993
          },
          {
            "text": "do",
            "boundingPolygon": [
              {
                "x": 615,
                "y": 1279
              },
              {
                "x": 665,
                "y": 1279
              },
              {
                "x": 664,
                "y": 1325
              },
              {
                "x": 615,
                "y": 1325
              }
            ],
            "confidence": 0.999
          },
          {
            "text": "amanh찾",
            "boundingPolygon": [
              {
                "x": 683,
                "y": 1279
              },
              {
                "x": 848,
                "y": 1279
              },
              {
                "x": 847,
                "y": 1325
              },
              {
                "x": 683,
                "y": 1325
              }
            ],
            "confidence": 0.993
          }
        ]
      },
      {
        "text": "COMPANHIA DAS LETRAS",
        "boundingPolygon": [
          {
            "x": 195,
            "y": 1381
          },
          {
            "x": 467,
            "y": 1381
          },
          {
            "x": 467,
            "y": 1407
          },
          {
            "x": 195,
            "y": 1407
          }
        ],
        "words": [
          {
            "text": "COMPANHIA",
            "boundingPolygon": [
              {
                "x": 197,
                "y": 1381
              },
              {
                "x": 327,
                "y": 1382
              },
              {
                "x": 327,
                "y": 1407
              },
              {
                "x": 196,
                "y": 1408
              }
            ],
            "confidence": 0.993
          },
          {
            "text": "DAS",
            "boundingPolygon": [
              {
                "x": 333,
                "y": 1382
              },
              {
                "x": 376,
                "y": 1382
              },
              {
                "x": 375,
                "y": 1407
              },
              {
                "x": 332,
                "y": 1407
              }
            ],
            "confidence": 0.993
          },
          {
            "text": "LETRAS",
            "boundingPolygon": [
              {
                "x": 382,
                "y": 1382
              },
              {
                "x": 466,
                "y": 1382
              },
              {
                "x": 465,
                "y": 1407
              },
              {
                "x": 381,
                "y": 1407
              }
            ],
            "confidence": 0.993
          }
        ]
      }
    ]
  }
]